MANIFEST.in
README.rst
setup.py
docs/COPYRIGHT.txt
docs/HISTORY.txt
docs/LICENSE.txt
src/cromlech/__init__.py
src/cromlech.marshallers.egg-info/PKG-INFO
src/cromlech.marshallers.egg-info/SOURCES.txt
src/cromlech.marshallers.egg-info/dependency_links.txt
src/cromlech.marshallers.egg-info/entry_points.txt
src/cromlech.marshallers.egg-info/namespace_packages.txt
src/cromlech.marshallers.egg-info/not-zip-safe
src/cromlech.marshallers.egg-info/requires.txt
src/cromlech.marshallers.egg-info/top_level.txt
src/cromlech/marshallers/__init__.py
src/cromlech/marshallers/_bson.py
src/cromlech/marshallers/_json.py
src/cromlech/marshallers/_marshal.py
src/cromlech/marshallers/_msgpack.py
src/cromlech/marshallers/_pickle.py
src/cromlech/marshallers/_rapidjson.py
src/cromlech/marshallers/_yaml.py
src/cromlech/marshallers/prototype.py
src/cromlech/marshallers/tests/test_bson.txt
src/cromlech/marshallers/tests/test_json.txt
src/cromlech/marshallers/tests/test_marshal.txt
src/cromlech/marshallers/tests/test_msgpack.txt
src/cromlech/marshallers/tests/test_pickle.txt
src/cromlech/marshallers/tests/test_rapidjson.txt
src/cromlech/marshallers/tests/test_yaml.txt