Metadata-Version: 2.1
Name: cromlech.marshallers
Version: 0.1
Summary: A collection of data marshallers for various generic uses
Home-page: https://github.com/Cromlech
Author: The Cromlecch Team
Author-email: dolmen@list.dolmen-project.org
License: ZPL
Keywords: Cromlech
Platform: UNKNOWN
Classifier: Programming Language :: Python
Provides-Extra: bson
Provides-Extra: msgpack
Provides-Extra: rapidjson
Provides-Extra: test
Provides-Extra: yaml
